{
    "arrow-*": {
        "Enabled": true,
        "Comment": "",
        "MorePilesProperties": {
            "ForceReplaceBehavior": true
        },
        "CtrlKey": false,
        "UpSolid": false,
        "BulkTransferQuantity": 8,
        "TransferQuantity": 1,
        "StackingCapacity": 64,
        "StackingModel": "morepiles:arrowpile_32",
        "CbScaleYByLayer": 0.25, // 16 / StackingCapacity,
        "CollisionBox": { "x1": 0, "y1": 0, "z1": 0, "x2": 1, "y2": 0.0625, "z2": 1 },
        "PlaceRemoveSound": "game:block/stickplace",
        "ModelItemsToStackSizeRatio": 6 // should be ??? / StackingCapacity
    },
    "chutesection-*": {
        "Enabled": true,
        "Comment": "",
        "MorePilesProperties": {
            "ForceReplaceBehavior": true
        },
        "CtrlKey": false,
        "UpSolid": true,
        "BulkTransferQuantity": 8,
        "TransferQuantity": 1,
        "StackingCapacity": 64,
        "StackingModel": "morepiles:chutesectionpile_8",
        "CbScaleYByLayer": 0.3125, // 20 / StackingCapacity,
        "CollisionBox": { "x1": 0, "y1": 0, "z1": 0, "x2": 1, "y2": 0.05, "z2": 1 },
        "PlaceRemoveSound": "game:block/chute",
        "ModelItemsToStackSizeRatio": 4
    },
    "metalchain-*": {
        "Enabled": true,
        "Comment": "",
        "MorePilesProperties": {
            "ForceReplaceBehavior": true
        },
        "CtrlKey": false,
        "UpSolid": false,
        "BulkTransferQuantity": 4,
        "TransferQuantity": 1,
        "StackingCapacity": 8,
        "StackingModel": "morepiles:metalchainpile_16",
        "CbScaleYByLayer": 1, // 8 / StackingCapacity,
        "CollisionBox": { "x1": 0.0315, "y1": 0, "z1": 0.0315, "x2": 0.9685, "y2": 0.125, "z2": 0.9685 },
        "PlaceRemoveSound": "game:wearable/chain1"
    },
    "metallamellae-*": {
        "Enabled": true,
        "Comment": "",
        "MorePilesProperties": {
            "ForceReplaceBehavior": true
        },
        "CtrlKey": false,
        "UpSolid": false,
        "BulkTransferQuantity": 4,
        "TransferQuantity": 1,
        "StackingCapacity": 8,
        "StackingModel": "morepiles:metallamellaepile_32",
        "CbScaleYByLayer": 1, // 8 / StackingCapacity,
        "CollisionBox": { "x1": 0.0315, "y1": 0, "z1": 0.0315, "x2": 0.9685, "y2": 0.125, "z2": 0.9685 },
        "PlaceRemoveSound": "game:wearable/chain1"
    },
    "metalscale-*": {
        "Enabled": true,
        "Comment": "",
        "MorePilesProperties": {
            "ForceReplaceBehavior": true
        },
        "CtrlKey": false,
        "UpSolid": false,
        "BulkTransferQuantity": 4,
        "TransferQuantity": 1,
        "StackingCapacity": 8,
        "StackingModel": "morepiles:metalscalespile_32",
        "CbScaleYByLayer": 1, // 8 / StackingCapacity,
        "CollisionBox": { "x1": 0.1875, "y1": 0, "z1": 0.1875, "x2": 0.8125, "y2": 0.125, "z2": 0.8125 },
        "PlaceRemoveSound": "game:wearable/chain1"
    },
    "rope": {
        "Enabled": true,
        "Comment": "Rope (vanilla)",
        "MorePilesProperties": {
            "FixPlacement": true,
            "ForceReplaceBehavior": true
        },
        "CtrlKey": true,
        "UpSolid": false,
        "BulkTransferQuantity": 4,
        "TransferQuantity": 1,
        "StackingCapacity": 32,
        "StackingModel": "morepiles:shapes/ropepile_32",
        "CbScaleYByLayer": 0.25, // 8 / StackingCapacity,
        "CollisionBox": { "x1": 0, "y1": 0, "z1": 0, "x2": 1, "y2": 0.125, "z2": 1 },
        "PlaceRemoveSound": "game:block/cloth"
    },
    "drygrass": {
        "Enabled": true,
        "Comment": "Dry grass (vanilla). Models: [ 'drygrasspile_64-optimized', 'drygrasspile_64-heavy' ]",
        "MorePilesProperties": {
            "FixPlacement": true,
            "ForceReplaceBehavior": true
        },
        "CtrlKey": true,
        "UpSolid": false,
        "BulkTransferQuantity": 4,
        "TransferQuantity": 1,
        "StackingCapacity": 64,
        "StackingModel": "morepiles:shapes/drygrasspile_64-optimized",
        "CbScaleYByLayer": 0.125, // 8 / StackingCapacity,
        "CollisionBox": { "x1": 0, "y1": 0, "z1": 0, "x2": 1, "y2": 0.125, "z2": 1 }
        // "PlaceRemoveSound": "game:block/cloth"
        // ModelItemsToStackSizeRatio info:
        // optimized - 11
        // heavy - 20
    },
    "snowball-*": {
        "Enabled": true,
        "Comment": "Snowball (vanilla)",
        "MorePilesProperties": {
            "FixPlacement": true,
            "ForceReplaceBehavior": true
        },
        "CtrlKey": true,
        "UpSolid": false,
        "BulkTransferQuantity": 6,
        "TransferQuantity": 1,
        "StackingCapacity": 11,
        "StackingModel": "morepiles:shapes/snowballpile-11",
        "PlaceRemoveSound": "game:block/snow",
        "collisionBox": { "x1": 0, "y1": 0, "z1": 0, "x2": 1, "y2": 0.25, "z2": 1 },
        "cbScaleYByLayer": 0.2
    }
}
